CHANGELOG.txt
LICENCE.txt
MANIFEST.in
README.txt
setup.py
ProductDetailFinder.egg-info/PKG-INFO
ProductDetailFinder.egg-info/SOURCES.txt
ProductDetailFinder.egg-info/dependency_links.txt
ProductDetailFinder.egg-info/requires.txt
ProductDetailFinder.egg-info/top_level.txt
productdetailfinder/__init__.py
productdetailfinder/__version__.py
productdetailfinder/constants.py
productdetailfinder/exception.py
productdetailfinder/productdetailfinder.py
productdetailfinder/util.py
venv/Lib/site-packages/easy_install.py
venv/Lib/site-packages/filelock.py
venv/Lib/site-packages/requests_file.py
venv/Lib/site-packages/six.py
venv/Lib/site-packages/_distutils_hack/__init__.py
venv/Lib/site-packages/_distutils_hack/override.py
venv/Lib/site-packages/amazon/__init__.py
venv/Lib/site-packages/amazon/constant.py
venv/Lib/site-packages/amazon/exception.py
venv/Lib/site-packages/amazon/paapi.py
venv/Lib/site-packages/amazon/parse.py
venv/Lib/site-packages/amazon/tools.py
venv/Lib/site-packages/certifi/__init__.py
venv/Lib/site-packages/certifi/__main__.py
venv/Lib/site-packages/certifi/core.py
venv/Lib/site-packages/certifi-2020.12.5.dist-info/top_level.txt
venv/Lib/site-packages/chardet/__init__.py
venv/Lib/site-packages/chardet/big5freq.py
venv/Lib/site-packages/chardet/big5prober.py
venv/Lib/site-packages/chardet/chardistribution.py
venv/Lib/site-packages/chardet/charsetgroupprober.py
venv/Lib/site-packages/chardet/charsetprober.py
venv/Lib/site-packages/chardet/codingstatemachine.py
venv/Lib/site-packages/chardet/compat.py
venv/Lib/site-packages/chardet/cp949prober.py
venv/Lib/site-packages/chardet/enums.py
venv/Lib/site-packages/chardet/escprober.py
venv/Lib/site-packages/chardet/escsm.py
venv/Lib/site-packages/chardet/eucjpprober.py
venv/Lib/site-packages/chardet/euckrfreq.py
venv/Lib/site-packages/chardet/euckrprober.py
venv/Lib/site-packages/chardet/euctwfreq.py
venv/Lib/site-packages/chardet/euctwprober.py
venv/Lib/site-packages/chardet/gb2312freq.py
venv/Lib/site-packages/chardet/gb2312prober.py
venv/Lib/site-packages/chardet/hebrewprober.py
venv/Lib/site-packages/chardet/jisfreq.py
venv/Lib/site-packages/chardet/jpcntx.py
venv/Lib/site-packages/chardet/langbulgarianmodel.py
venv/Lib/site-packages/chardet/langcyrillicmodel.py
venv/Lib/site-packages/chardet-3.0.4.dist-info/entry_points.txt
venv/Lib/site-packages/chardet-3.0.4.dist-info/top_level.txt
venv/Lib/site-packages/filelock-3.0.12.dist-info/top_level.txt
venv/Lib/site-packages/idna-2.10.dist-info/top_level.txt
venv/Lib/site-packages/pip-20.3.1.dist-info/LICENSE.txt
venv/Lib/site-packages/pip-20.3.1.dist-info/entry_points.txt
venv/Lib/site-packages/pip-20.3.1.dist-info/top_level.txt
venv/Lib/site-packages/python_amazon_paapi-3.3.1.dist-info/top_level.txt
venv/Lib/site-packages/python_dateutil-2.8.1.dist-info/top_level.txt
venv/Lib/site-packages/requests-2.25.0.dist-info/top_level.txt
venv/Lib/site-packages/requests_file-1.5.1.dist-info/top_level.txt
venv/Lib/site-packages/setuptools-51.0.0.dist-info/dependency_links.txt
venv/Lib/site-packages/setuptools-51.0.0.dist-info/entry_points.txt
venv/Lib/site-packages/setuptools-51.0.0.dist-info/top_level.txt
venv/Lib/site-packages/six-1.15.0.dist-info/top_level.txt
venv/Lib/site-packages/tldextract-3.1.0.dist-info/entry_points.txt
venv/Lib/site-packages/tldextract-3.1.0.dist-info/top_level.txt
venv/Lib/site-packages/urllib3-1.26.2.dist-info/LICENSE.txt
venv/Lib/site-packages/urllib3-1.26.2.dist-info/top_level.txt
