Metadata-Version: 1.1
Name: ProductDetailFinder
Version: 1.0.0
Summary: Amazon Flipkart product detail finder
Home-page: UNKNOWN
Author: Manoj Sitapara
Author-email: manojsitapara@gmail.com
License: MIT
Keywords: Amazon Flipkart
Platform: UNKNOWN
Classifier: Development Status :: 5 - Production/Stable
Classifier: Intended Audience :: Education
Classifier: Operating System :: Microsoft :: Windows :: Windows 10
Classifier: License :: OSI Approved :: MIT License
Classifier: Programming Language :: Python :: 3
